eve_resource/__init__.py
eve_resource/event.py
eve_resource/exceptions.py
eve_resource/hooks.py
eve_resource/resource.py
eve_resource/utils.py
eve_resource-0.1.5.dist-info/DESCRIPTION.rst
eve_resource-0.1.5.dist-info/METADATA
eve_resource-0.1.5.dist-info/RECORD
eve_resource-0.1.5.dist-info/WHEEL
eve_resource-0.1.5.dist-info/metadata.json
eve_resource-0.1.5.dist-info/top_level.txt
tests/__init__.py
tests/test_events.py
tests/test_exceptions.py
tests/test_hooks.py
tests/test_resource.py
tests/test_utils.py
