Metadata-Version: 2.0
Name: eve-resource
Version: 0.1.5
Summary: Resource utilities for Eve
Home-page: https://github.com/m-housh/eve_resource
Author: Michael Housh
Author-email: mhoush@houshhomeenergy.com
License: MIT license
Keywords: eve_resource
Platform: UNKNOWN
Classifier: Development Status :: 2 - Pre-Alpha
Classifier: Intended Audience :: Developers
Classifier: License :: OSI Approved :: MIT License
Classifier: Natural Language :: English
Classifier: Programming Language :: Python :: 2
Classifier: Programming Language :: Python :: 2.6
Classifier: Programming Language :: Python :: 2.7
Classifier: Programming Language :: Python :: 3
Classifier: Programming Language :: Python :: 3.3
Classifier: Programming Language :: Python :: 3.4
Classifier: Programming Language :: Python :: 3.5
Requires-Dist: Eve (>=0.6.4)
